ankcompiler-0.1.5.dist-info/METADATA
ankcompiler-0.1.5.dist-info/WHEEL
ankcompiler-0.1.5.dist-info/entry_points.txt
ankcompiler-0.1.5.dist-info/licenses/LICENSE.md
app/__init__.py
app/cli/__init__.py
app/cli/build.py
app/cli/entry.py
app/cli/gen.py
app/cli/list.py
app/config.py
app/logic/__init__.py
app/logic/drivers.py
app/logic/sources.py
app/logic/utils.py
app/main.py
ankcompiler-0.1.5.dist-info/RECORD
