Metadata-Version: 2.1
Name: ankcompiler
Version: 0.1.5
Summary: A CLI tool for compiling Anki decks, defined in Markdown
Author-Email: Quinn Herden <55929299+QuinnHerden@users.noreply.github.com>
License: MIT
Requires-Python: >=3.11
Requires-Dist: typer>=0.12.3
Requires-Dist: genanki>=0.13.1
Requires-Dist: toml>=0.10.2
Requires-Dist: pydantic>=2.7.4
Requires-Dist: pydantic-settings>=2.3.4
Requires-Dist: dataclasses>=0.6
Requires-Dist: python-frontmatter>=1.1.0
Requires-Dist: markdown>=3.6
